django_rulebase/__init__.py
django_rulebase/request.py
django_rulebase/rule.py
django_rulebase/validator.py
django_rulebase-0.1.3.dist-info/LICENSE
django_rulebase-0.1.3.dist-info/METADATA
django_rulebase-0.1.3.dist-info/WHEEL
django_rulebase-0.1.3.dist-info/top_level.txt
django_rulebase-0.1.3.dist-info/RECORD
