Metadata-Version: 2.1
Name: django-rulebase
Version: 0.1.3
Summary: Django rule base validation , inspired by laravel Request
Home-page: https://github.com/mojtabaasadi/django-rulebase
Author: Mojtaba Asadi
Author-email: m.asadi.al@outlook.com
Classifier: Programming Language :: Python :: 2.7
Classifier: Programming Language :: Python :: 3
Classifier: License :: OSI Approved :: GNU General Public License v3 (GPLv3)
Classifier: Framework :: Django
Classifier: Operating System :: OS Independent
License-File: LICENSE
Requires-Dist: dateparser
Requires-Dist: dnspython
Requires-Dist: pytz
Requires-Dist: django
